h5md/__init__.py
h5md/cli.py
h5md-0.1.0.dist-info/licenses/LICENSE
h5md-0.1.0.dist-info/METADATA
h5md-0.1.0.dist-info/WHEEL
h5md-0.1.0.dist-info/entry_points.txt
h5md-0.1.0.dist-info/top_level.txt
h5md-0.1.0.dist-info/RECORD
