Metadata-Version: 2.4
Name: h5md
Version: 0.1.0
Summary: A command-line tool to convert HDF5 files to markdown format
Home-page: https://github.com/hyoklee/h5md
Author: Joe Lee
Author-email: Joe Lee <hyoklee@hdfgroup.org>
Project-URL: Homepage, https://github.com/hyoklee/h5md
Project-URL: Documentation, https://github.com/hyoklee/h5md/blob/main/README.md
Project-URL: Repository, https://github.com/hyoklee/h5md.git
Project-URL: Issues, https://github.com/hyoklee/h5md/issues
Keywords: hdf5,markdown,converter,documentation
Classifier: Development Status :: 3 - Alpha
Classifier: Intended Audience :: Science/Research
Classifier: Operating System :: OS Independent
Classifier: Programming Language :: Python :: 3
Classifier: Programming Language :: Python :: 3.10
Classifier: Programming Language :: Python :: 3.11
Classifier: Topic :: Scientific/Engineering
Classifier: Topic :: Text Processing :: Markup :: Markdown
Requires-Python: >=3.10
License-File: LICENSE
Requires-Dist: h5py>=3.0.0
Requires-Dist: numpy>=1.20.0
Provides-Extra: dev
Requires-Dist: pytest>=7.0.0; extra == "dev"
Requires-Dist: pytest-cov>=4.0.0; extra == "dev"
Requires-Dist: black>=23.3.0; extra == "dev"
Requires-Dist: isort>=5.12.0; extra == "dev"
Requires-Dist: flake8>=6.0.0; extra == "dev"
Requires-Dist: mypy>=1.3.0; extra == "dev"
Requires-Dist: twine>=4.0.0; extra == "dev"
Requires-Dist: build>=0.10.0; extra == "dev"
Dynamic: author
Dynamic: home-page
Dynamic: license-file
Dynamic: requires-python
